pypg/__init__.py
pypg/cycles.py
pypg/features.py
pypg/filters.py
pypg/plots.py
pypg-0.0.5.dist-info/LICENSE
pypg-0.0.5.dist-info/METADATA
pypg-0.0.5.dist-info/WHEEL
pypg-0.0.5.dist-info/top_level.txt
pypg-0.0.5.dist-info/RECORD
