Metadata-Version: 2.1
Name: pypg
Version: 0.0.5
Summary: PyPG: A library for PPG (PhotoPlethysmoGram) processing
Home-page: https://github.com/hpi-dhc/pypg
Author: Ariane Sasso
Author-email: ariane.sasso@gmail.com
License: UNKNOWN
Platform: UNKNOWN
Classifier: Programming Language :: Python :: 3
Classifier: License :: OSI Approved :: MIT License
Classifier: Operating System :: OS Independent
Requires-Python: >=3.6
License-File: LICENSE
Requires-Dist: matplotlib
Requires-Dist: numpy
Requires-Dist: pandas
Requires-Dist: scipy
